ddsapi/__init__.py
ddsapi/api.py
ddsapi/cache.py
eo4eu_ddsapi-0.7.2.dist-info/METADATA
eo4eu_ddsapi-0.7.2.dist-info/WHEEL
eo4eu_ddsapi-0.7.2.dist-info/top_level.txt
eo4eu_ddsapi-0.7.2.dist-info/RECORD
