Metadata-Version: 2.4
Name: eo4eu-ddsapi
Version: 0.7.2
Summary: EO4EU fork of official ddsapi package
Author-email: CMCC Data Delivery System Team <dds-support@cmcc.it>, Apollon Grigoras <apollon@uoa.gr>
License-Expression: Apache-2.0
Classifier: Development Status :: 4 - Beta
Classifier: Environment :: Web Environment
Classifier: Intended Audience :: Science/Research
Classifier: Natural Language :: English
Classifier: Operating System :: OS Independent
Classifier: Programming Language :: Python :: 3
Classifier: Programming Language :: Python :: 3.11
Classifier: Programming Language :: Python :: 3.12
Classifier: Topic :: Scientific/Engineering :: Atmospheric Science
Classifier: Topic :: Scientific/Engineering :: Hydrology
Requires-Python: >=3.11
Requires-Dist: requests>=2.23.0
Requires-Dist: xarray>=2022.10.0
